{
  "slug": "tintin-reporter---cigars-of-the-pharaoh-limited-edition-نسخه-استیل-بوک",
  "igdb_id": 242368,
  "name": "Tintin Reporter: Cigars of the Pharaoh - Limited Edition",
  "summary": "Tintin Reporter: Cigars of the Pharaoh - Limited Edition is an adventure game that combines exploration, puzzle-solving, and stealth elements as players investigate interconnected locations inspired by the classic comic. Gameplay focuses on navigating varied environments, interacting with characters, and uncovering clues through a mix of action and logic-based challenges.\n\nThis edition includes:\n- The retail version of the game\n- An official Steelbook\n- Three postcards",
  "first_release_year": 2023,
  "developers": [
    "Pendulo Studios"
  ],
  "publishers": [
    "Microids"
  ],
  "genres": [
    "Adventure"
  ],
  "themes": [
    "Action",
    "Comedy"
  ],
  "game_modes": [
    "Single player"
  ],
  "player_perspectives": [],
  "series": [],
  "spin_off_of": null,
  "franchises": [
    "Adventures of Tintin"
  ],
  "game_engines": [],
  "keywords": [],
  "alternative_names": [],
  "websites": [
    {
      "label": "Official Website",
      "url": "https://www.microids.com/game-tintin-reporter-cigars-of-the-pharaoh/"
    }
  ],
  "release_dates": [
    {
      "platform": "Nintendo Switch",
      "region": null,
      "date": "Oct 17, 2024",
      "status": "Cancelled",
      "date_iso": "2024-10-17"
    },
    {
      "platform": "PlayStation 5",
      "region": null,
      "date": "Nov 07, 2023",
      "status": "Cancelled",
      "date_iso": "2023-11-07"
    },
    {
      "platform": "Xbox One",
      "region": null,
      "date": "Nov 07, 2023",
      "status": "Cancelled",
      "date_iso": "2023-11-07"
    },
    {
      "platform": "Xbox Series X|S",
      "region": null,
      "date": "Nov 07, 2023",
      "status": "Cancelled",
      "date_iso": "2023-11-07"
    },
    {
      "platform": "PlayStation 4",
      "region": null,
      "date": "Nov 07, 2023",
      "status": "Cancelled",
      "date_iso": "2023-11-07"
    }
  ],
  "artworks": [
    "https://images.igdb.com/igdb/image/upload/t_1080p/ar5obf.jpg"
  ],
  "videos": []
}